livecc_utils/__init__.py
livecc_utils/generation_patch.py
livecc_utils/video_process_patch.py
livecc_utils-0.0.2.dist-info/METADATA
livecc_utils-0.0.2.dist-info/WHEEL
livecc_utils-0.0.2.dist-info/RECORD
